professor-0.1.0.dist-info/licenses/LICENSE
strictpy/__init__.py
strictpy/private.py
strictpy/singleton.py
professor-0.1.0.dist-info/METADATA
professor-0.1.0.dist-info/WHEEL
professor-0.1.0.dist-info/top_level.txt
professor-0.1.0.dist-info/RECORD
