Metadata-Version: 2.4
Name: professor
Version: 0.1.0
Summary: Java/C# style access modifiers and patterns for Python
Author-email: Your Name <you@example.com>
License: MIT License
Project-URL: Homepage, https://github.com/VibhinnS/strictpy
Project-URL: Bug Tracker, https://github.com/VibhinnS/strictpy/issues
Keywords: python,decorators,access control,singleton,private
Classifier: Programming Language :: Python :: 3
Classifier: License :: OSI Approved :: MIT License
Classifier: Operating System :: OS Independent
Requires-Python: >=3.8
License-File: LICENSE
Dynamic: license-file
